ollama_local_serve/__init__.py
ollama_local_serve/client.py
ollama_local_serve/config.py
ollama_local_serve/exceptions.py
ollama_local_serve/service.py
ollama_local_serve/api/__init__.py
ollama_local_serve/api/dependencies.py
ollama_local_serve/api/gpu_monitor.py
ollama_local_serve/api/metrics_collector.py
ollama_local_serve/api/models.py
ollama_local_serve/api/server.py
ollama_local_serve/exporters/__init__.py
ollama_local_serve/exporters/base.py
ollama_local_serve/exporters/clickhouse_exporter.py
ollama_local_serve/exporters/postgres_exporter.py
ollama_local_serve/instrumentation/__init__.py
ollama_local_serve/instrumentation/metrics_provider.py
ollama_local_serve/instrumentation/tracer.py
ollama_local_serve-0.2.5.dist-info/licenses/LICENSE
ollama_local_serve-0.2.5.dist-info/METADATA
ollama_local_serve-0.2.5.dist-info/WHEEL
ollama_local_serve-0.2.5.dist-info/entry_points.txt
ollama_local_serve-0.2.5.dist-info/top_level.txt
ollama_local_serve-0.2.5.dist-info/RECORD
