Metadata-Version: 2.4
Name: ollama-local-serve
Version: 0.2.5
Summary: Local LLM infrastructure with monitoring dashboard for distributed AI applications
Author: Abhinaav Ramesh
License-Expression: MIT
Project-URL: Homepage, https://github.com/AbhinaavRamesh/ollama-local-serve
Project-URL: Repository, https://github.com/AbhinaavRamesh/ollama-local-serve
Project-URL: Documentation, https://github.com/AbhinaavRamesh/ollama-local-serve#readme
Project-URL: Issues, https://github.com/AbhinaavRamesh/ollama-local-serve/issues
Keywords: ollama,llm,langchain,ai,local,serve,monitoring,metrics,opentelemetry,dashboard
Classifier: Development Status :: 4 - Beta
Classifier: Intended Audience :: Developers
Classifier: Programming Language :: Python :: 3
Classifier: Programming Language :: Python :: 3.12
Classifier: Programming Language :: Python :: 3.13
Classifier: Framework :: FastAPI
Classifier: Topic :: Scientific/Engineering :: Artificial Intelligence
Classifier: Topic :: System :: Monitoring
Requires-Python: >=3.12
License-File: LICENSE
Requires-Dist: aiohttp>=3.8.0
Requires-Dist: httpx>=0.25.0
Requires-Dist: pydantic>=2.0.0
Requires-Dist: pydantic-settings>=2.0.0
Provides-Extra: langchain
Requires-Dist: langchain>=0.1.0; extra == "langchain"
Requires-Dist: langchain-community>=0.0.10; extra == "langchain"
Requires-Dist: langchain-ollama>=0.1.0; extra == "langchain"
Provides-Extra: langgraph
Requires-Dist: ollama-local-serve[langchain]; extra == "langgraph"
Requires-Dist: langgraph>=0.2.0; extra == "langgraph"
Provides-Extra: api
Requires-Dist: fastapi>=0.104.0; extra == "api"
Requires-Dist: uvicorn[standard]>=0.24.0; extra == "api"
Requires-Dist: python-multipart>=0.0.6; extra == "api"
Requires-Dist: python-dotenv>=1.0.0; extra == "api"
Requires-Dist: orjson>=3.9.0; extra == "api"
Provides-Extra: instrumentation
Requires-Dist: opentelemetry-api>=1.20.0; extra == "instrumentation"
Requires-Dist: opentelemetry-sdk>=1.20.0; extra == "instrumentation"
Requires-Dist: opentelemetry-exporter-otlp>=1.20.0; extra == "instrumentation"
Requires-Dist: opentelemetry-instrumentation-fastapi>=0.41b0; extra == "instrumentation"
Requires-Dist: opentelemetry-instrumentation-httpx>=0.41b0; extra == "instrumentation"
Provides-Extra: clickhouse
Requires-Dist: clickhouse-driver>=0.2.6; extra == "clickhouse"
Requires-Dist: clickhouse-connect>=0.6.0; extra == "clickhouse"
Provides-Extra: postgres
Requires-Dist: sqlalchemy[asyncio]>=2.0.0; extra == "postgres"
Requires-Dist: asyncpg>=0.29.0; extra == "postgres"
Requires-Dist: psycopg2-binary>=2.9.0; extra == "postgres"
Provides-Extra: exporters
Requires-Dist: ollama-local-serve[clickhouse,postgres]; extra == "exporters"
Provides-Extra: monitoring
Requires-Dist: ollama-local-serve[api,exporters,instrumentation]; extra == "monitoring"
Requires-Dist: structlog>=23.0.0; extra == "monitoring"
Requires-Dist: python-json-logger>=2.0.0; extra == "monitoring"
Requires-Dist: tenacity>=8.2.0; extra == "monitoring"
Provides-Extra: all
Requires-Dist: ollama-local-serve[langgraph,monitoring]; extra == "all"
Provides-Extra: dev
Requires-Dist: pytest>=7.0.0; extra == "dev"
Requires-Dist: pytest-asyncio>=0.21.0; extra == "dev"
Requires-Dist: pytest-cov>=4.0.0; extra == "dev"
Requires-Dist: black>=23.0.0; extra == "dev"
Requires-Dist: mypy>=1.0.0; extra == "dev"
Requires-Dist: ruff>=0.1.0; extra == "dev"
Requires-Dist: pre-commit>=3.0.0; extra == "dev"
Requires-Dist: httpx>=0.25.0; extra == "dev"
Provides-Extra: docs
Requires-Dist: mkdocs>=1.5.0; extra == "docs"
Requires-Dist: mkdocs-material>=9.0.0; extra == "docs"
Requires-Dist: mkdocstrings[python]>=0.24.0; extra == "docs"
Dynamic: license-file
